{
    "keep": {
        "days": true,
        "amount": 14
    },
    "auditLog": "D:\\int_installation_file\\ahfl-customer-app-node-backend\\logs\\.90ce8eee68714f84904ecd94915f5f92bcffb4ff-audit.json",
    "files": [
        {
            "date": 1765335374367,
            "name": "D:\\int_installation_file\\ahfl-customer-app-node-backend\\logs\\exceptions-2025-12-10.log",
            "hash": "06954af3e50696c15399ed6cd6aed0686791857551af580b473022d5686e1a05"
        },
        {
            "date": 1765440903101,
            "name": "D:\\int_installation_file\\ahfl-customer-app-node-backend\\logs\\exceptions-2025-12-11.log",
            "hash": "9fec07ae02b34b878a84be23eb35b64f013823d9e12fa6cd1dd291c7e52850a5"
        },
        {
            "date": 1765521434262,
            "name": "D:\\int_installation_file\\ahfl-customer-app-node-backend\\logs\\exceptions-2025-12-12.log",
            "hash": "51acf0d51f117aaf0a4084a53a47e40855c944fd0776996cdf1642eedd27d1b4"
        },
        {
            "date": 1765599538382,
            "name": "D:\\int_installation_file\\ahfl-customer-app-node-backend\\logs\\exceptions-2025-12-13.log",
            "hash": "2c5b9fcedaa29b90ce0059ed937f3b0882cd0ef8a2ae493b7fbe1fff34708021"
        },
        {
            "date": 1765819274198,
            "name": "D:\\int_installation_file\\ahfl-customer-app-node-backend\\logs\\exceptions-2025-12-15.log",
            "hash": "fd90cbb5fe2dabf67e83dc52aceacc165f5b1f0d64a838369eec60ca7d9d4262"
        },
        {
            "date": 1765868903027,
            "name": "D:\\int_installation_file\\ahfl-customer-app-node-backend\\logs\\exceptions-2025-12-16.log",
            "hash": "78cd2ced502fc3f7dd714ee9a8388766a0cdce9613d99b26ca63ea4be64f533f"
        },
        {
            "date": 1765910246196,
            "name": "D:\\int_installation_file\\ahfl-customer-app-node-backend\\logs\\exceptions-2025-12-17.log",
            "hash": "919c9cc030c37e8cbd606d27cbd5ad0080ff3446ac37dad0584a919406e44d4f"
        },
        {
            "date": 1766028209939,
            "name": "D:\\int_installation_file\\ahfl-customer-app-node-backend\\logs\\exceptions-2025-12-18.log",
            "hash": "c767450fd617c4af8685f3c7db92d4f5e0d28cc294bdd1394c0c9e9acbbffbcd"
        },
        {
            "date": 1766109623696,
            "name": "D:\\int_installation_file\\ahfl-customer-app-node-backend\\logs\\exceptions-2025-12-19.log",
            "hash": "e7b200e3bf7a75e6a1bcb4f2541ed3a5d4890428ce2f778081d166c310944e44"
        },
        {
            "date": 1766201965745,
            "name": "D:\\int_installation_file\\ahfl-customer-app-node-backend\\logs\\exceptions-2025-12-20.log",
            "hash": "e735dce1fa764a9de3b564946badcad1def761fe17f368f1b946986119725155"
        },
        {
            "date": 1766282426175,
            "name": "D:\\int_installation_file\\ahfl-customer-app-node-backend\\logs\\exceptions-2025-12-21.log",
            "hash": "27c784a311976d5a0f86185bcecfaa9fdd5b9950b6bd7fccb6ca88d31e8eb232"
        },
        {
            "date": 1766368611906,
            "name": "D:\\int_installation_file\\ahfl-customer-app-node-backend\\logs\\exceptions-2025-12-22.log",
            "hash": "c1aa63a45b06f4fae075115b271ee282a871d230c06dcc406cef2c0b3c8f09b1"
        },
        {
            "date": 1766455230003,
            "name": "D:\\int_installation_file\\ahfl-customer-app-node-backend\\logs\\exceptions-2025-12-23.log",
            "hash": "b44063834732df72b62b9ffa1554814038593b116022b6cbe8236e38f6212c5e"
        },
        {
            "date": 1766514982816,
            "name": "D:\\int_installation_file\\ahfl-customer-app-node-backend\\logs\\exceptions-2025-12-24.log",
            "hash": "7e3e7fd4887b877b066e320fdd31d5ca25d8e2ad4272b63f20b3cdfc7b907e1c"
        }
    ],
    "hashType": "sha256"
}